tyfbaf/__init__.py
tyfbaf/cmsquery.py
tyfbaf/cmsquery_utils.py
tyfbaf/http.py
tyfbaf/token.py
tyfbaf-0.0.6.dist-info/LICENSE
tyfbaf-0.0.6.dist-info/WHEEL
tyfbaf-0.0.6.dist-info/METADATA
tyfbaf-0.0.6.dist-info/RECORD
