Metadata-Version: 2.1
Name: tyfbaf
Version: 0.0.6
Summary: tyfbaf
Author: Yves Oehlschläger
Requires-Python: >=3.9
Classifier: License :: OSI Approved :: MIT License
Requires-Dist: httpx
Requires-Dist: black ; extra == "dev"
Project-URL: Home, https://github.com/yveso/tyfbaf
Provides-Extra: dev
